ccdexplorer_schema_parser-0.1.14.dist-info/METADATA
ccdexplorer_schema_parser-0.1.14.dist-info/WHEEL
ccdexplorer_schema_parser-0.1.14.dist-info/license_files/LICENSE.md
ccdexplorer_schema_parser/__init__.py
ccdexplorer_schema_parser/Schema.py
ccdexplorer_schema_parser/ccdexplorer_schema_parser.cpython-311-darwin.so
ccdexplorer_schema_parser-0.1.14.dist-info/RECORD
