Metadata-Version: 2.3
Name: ccdexplorer-schema-parser
Version: 0.1.14
Classifier: Programming Language :: Rust
Classifier: Programming Language :: Python :: Implementation :: CPython
Classifier: Programming Language :: Python :: Implementation :: PyPy
License-File: LICENSE.md
Requires-Python: >=3.8
